flappy_bird/__init__.py
flappy_bird/game_engine.py
flappy_bird_engine-0.0.4.data/data/assets/Bird.png
flappy_bird_engine-0.0.4.data/data/assets/Ground.png
flappy_bird_engine-0.0.4.data/data/assets/bg.png
flappy_bird_engine-0.0.4.data/data/assets/pipe.png
src/__init__.py
src/bird.py
src/game_object.py
src/pipe.py
flappy_bird_engine-0.0.4.dist-info/LICENSE
flappy_bird_engine-0.0.4.dist-info/METADATA
flappy_bird_engine-0.0.4.dist-info/WHEEL
flappy_bird_engine-0.0.4.dist-info/top_level.txt
flappy_bird_engine-0.0.4.dist-info/RECORD
