Metadata-Version: 2.1
Name: flappy-bird-engine
Version: 0.0.4
Summary: A game engine for Flappy Bird powered by Pygame.
Home-page: https://github.com/JoshuaBillson/Flappy_Bird_Engine.git
Author: Joshua Billson
Author-email: jmbillson@outlook.com
License: UNKNOWN
Platform: UNKNOWN
Classifier: Programming Language :: Python :: 3
Classifier: License :: OSI Approved :: MIT License
Classifier: Operating System :: OS Independent
Requires-Python: >=3.7
Requires-Dist: pygame (==1.9.6)
Requires-Dist: wheel (==0.34.2)
